prepmagma/__init__.py
prepmagma/db.py
prepmagma/geneset.py
prepmagma/res.py
prepmagma-0.2.2.dist-info/METADATA
prepmagma-0.2.2.dist-info/WHEEL
prepmagma-0.2.2.dist-info/RECORD
